literature_game_engine_raspuchin/Card.py
literature_game_engine_raspuchin/CardsHelper.py
literature_game_engine_raspuchin/Hand.py
literature_game_engine_raspuchin/Literature.py
literature_game_engine_raspuchin/Players.py
literature_game_engine_raspuchin/__init__.py
literature_game_engine_raspuchin-0.0.1.dist-info/LICENSE
literature_game_engine_raspuchin-0.0.1.dist-info/METADATA
literature_game_engine_raspuchin-0.0.1.dist-info/WHEEL
literature_game_engine_raspuchin-0.0.1.dist-info/top_level.txt
literature_game_engine_raspuchin-0.0.1.dist-info/RECORD
