Metadata-Version: 2.1
Name: literature-game-engine-raspuchin
Version: 0.0.1
Summary: Package to provide a game engine to play literature.
Author-email: Sachin Pothukuchi <sachinpothukuchi31@gmail.com>
Project-URL: Homepage, https://github.com/raspuchin/literature-game
Project-URL: Bug Tracker, https://github.com/raspuchin/literature-game/issues
Classifier: Programming Language :: Python :: 3
Classifier: License :: OSI Approved :: MIT License
Classifier: Operating System :: OS Independent
Requires-Python: >=3.7
License-File: LICENSE
